{
    "time": 1687978868,
    "sport": "Cycling",
    "type": "",
    "timezone_offset": null,
    "created": null,
    "edited": null,
    "public": false,
    "track": false,
    "distance": null,
    "duration": null,
    "elapsedTime": null,
    "elevationUp": null,
    "elevationDown": null,
    "elevationUpFile": null,
    "elevationDownFile": null,
    "altitudeSource": 0,
    "climbScore": null,
    "percentageHilly": null,
    "uphillEfficiency": null,
    "downhillEfficiency": null,
    "vam": null,
    "kcal": null,
    "hrAvg": null,
    "hrMax": null,
    "recoveryHr": null,
    "maxHeartRateDropFrom": null,
    "maxHeartRateDrop": null,
    "vo2max": null,
    "vo2maxByTime": null,
    "vo2maxWithElevation": null,
    "useVo2max": true,
    "fitVO2maxEstimate": null,
    "fitRecoveryTime": null,
    "fitHrvAnalysis": null,
    "fitTrainingEffect": null,
    "fitAnaerobicTrainingEffect": null,
    "fitTrimp": null,
    "fitSweatLoss": null,
    "fitPerformanceCondition": null,
    "fitPerformanceConditionEnd": null,
    "fitFtp": null,
    "fitDeveloperSessionFields": null,
    "rpe": null,
    "subjectiveFeeling": null,
    "trimp": null,
    "peakEpoc": null,
    "peakEpocEstimate": null,
    "cadence": null,
    "gap": null,
    "xPace": null,
    "xGap": null,
    "aerobicDecouplingPace": null,
    "aerobicDecouplingPower": null,
    "power": null,
    "powerWithZero": null,
    "airPower": null,
    "isPowerCalculated": null,
    "xPower": null,
    "xPowerWithZero": null,
    "w_prime_balance_power_avg": null,
    "w_prime_balance_power_min": null,
    "w_prime_balance_pace_avg": null,
    "w_prime_balance_pace_min": null,
    "stamina_avg": null,
    "stamina_min": null,
    "stamina_potential_avg": null,
    "stamina_potential_min": null,
    "required_critical_power": null,
    "required_critical_pace": null,
    "required_critical_pace_vo2max": null,
    "impact_load_factor_avg": null,
    "step_speed_loss_avg": null,
    "zoneDistributionPace": null,
    "zoneDistributionHr": null,
    "zoneDistributionPower": null,
    "totalStrokes": null,
    "swolf": null,
    "poolLength": null,
    "strideLength": null,
    "groundcontact": null,
    "groundcontactBalance": null,
    "verticalOscillation": null,
    "verticalRatio": null,
    "avgImpactGsLeft": null,
    "avgImpactGsRight": null,
    "avgBrakingGsLeft": null,
    "avgBrakingGsRight": null,
    "avgFootstrikeTypeLeft": null,
    "avgFootstrikeTypeRight": null,
    "avgPronationExcursionLeft": null,
    "avgPronationExcursionRight": null,
    "avgLegSpringStiffness": null,
    "avgFormPower": null,
    "avgRespiratoryRate": null,
    "avgLeftRightBalance": null,
    "avgLeftTorqueEffectiveness": null,
    "avgRightTorqueEffectiveness": null,
    "avgLeftPedalSmoothness": null,
    "avgRightPedalSmoothness": null,
    "avgPlatformCenterOffsetLeft": null,
    "avgPlatformCenterOffsetRight": null,
    "avgLeftPowerPhaseStartAngle": null,
    "avgLeftPowerPhaseEndAngle": null,
    "avgLeftPowerPhasePeakStartAngle": null,
    "avgLeftPowerPhasePeakEndAngle": null,
    "avgRightPowerPhaseStartAngle": null,
    "avgRightPowerPhaseEndAngle": null,
    "avgRightPowerPhasePeakStartAngle": null,
    "avgRightPowerPhasePeakEndAngle": null,
    "cyclingAvgFlow": null,
    "cyclingTotalGrit": null,
    "jumps": null,
    "percentageRiderPositionSeated": null,
    "numGearChangeEvents": null,
    "avgGearRatio": null,
    "wheelSize": null,
    "splits": null,
    "splitsCustom": null,
    "temperature": null,
    "windSpeed": null,
    "windDeg": null,
    "humidity": null,
    "cloudCover": null,
    "pressure": null,
    "uvIndex": null,
    "ozone": null,
    "isNight": null,
    "weatherid": 1,
    "weatherSource": null,
    "routeName": null,
    "isVirtual": false,
    "title": null,
    "partner": null,
    "notes": null,
    "deviceId": null,
    "creator": "",
    "creatorDetails": null,
    "source": 0,
    "externalId": null,
    "hrv": null,
    "athleteData": {
        "date": null,
        "weight": 77.2,
        "maximal_heart_rate": 196,
        "resting_heart_rate": 58,
        "fat_percentage": null,
        "water_percentage": null,
        "muscle_percentage": null,
        "bone_percentage": null,
        "ftp": [],
        "cp": [],
        "w_prime": [],
        "pace_ftp": [],
        "pace_cp": [],
        "pace_w_prime": [],
        "lactate_threshold_pace": [],
        "lactate_threshold_heart_rate": [],
        "lactate_threshold_power": []
    },
    "workout": null,
    "lastCalculation": null,
    "trackdataFileFormat": ".json.gz",
    "startpoint": "u0u673f5g1",
    "endpoint": "u0u673fj2p",
    "point_min": "u0u670rvgk",
    "point_max": "u0u6yy09rr",
    "in_routenet": false,
    "climbs": [
        {
            "category": 4,
            "name": null,
            "fiets": 1.1,
            "distance": 0.61,
            "duration": 73,
            "ascent": 60,
            "altitude_at_top": 321,
            "starts_at": 1.63,
            "end_geohash": "u0u678yc8h",
            "avg_power": 404
        },
        {
            "category": 5,
            "name": null,
            "fiets": 0.3,
            "distance": 3.79,
            "duration": 531,
            "ascent": 63,
            "altitude_at_top": 378,
            "starts_at": 2.47,
            "end_geohash": "u0u6ks5wqc",
            "avg_power": 141
        },
        {
            "category": 5,
            "name": null,
            "fiets": 0.4,
            "distance": 1.04,
            "duration": 278,
            "ascent": 47,
            "altitude_at_top": 363,
            "starts_at": 18.23,
            "end_geohash": "u0u6y924ug",
            "avg_power": 169
        },
        {
            "category": 4,
            "name": null,
            "fiets": 0.7,
            "distance": 2.95,
            "duration": 563,
            "ascent": 79,
            "altitude_at_top": 378,
            "starts_at": 21.05,
            "end_geohash": "u0u6vtsswt",
            "avg_power": 97
        },
        {
            "category": 4,
            "name": null,
            "fiets": 0.5,
            "distance": 1.52,
            "duration": 215,
            "ascent": 47,
            "altitude_at_top": 359,
            "starts_at": 29.96,
            "end_geohash": "u0u6seu7pq",
            "avg_power": 162
        },
        {
            "category": 4,
            "name": null,
            "fiets": 0.8,
            "distance": 1.45,
            "duration": 299,
            "ascent": 68,
            "altitude_at_top": 423,
            "starts_at": 32.83,
            "end_geohash": "u0u6krzrrz",
            "avg_power": 151
        },
        {
            "category": 4,
            "name": null,
            "fiets": 0.8,
            "distance": 2.61,
            "duration": 635,
            "ascent": 97,
            "altitude_at_top": 334,
            "starts_at": 39.17,
            "end_geohash": "u0u673fj2p",
            "avg_power": 104
        }
    ],
    "stream": [
        {
            "Duration": [],
            "Distance": [],
            "Geohashes": [],
            "AltitudeOriginal": [],
            "AltitudeCorrected": [],
            "OriginalPace": [],
            "OriginalGradeAdjustedPace": [],
            "HeartRate": [],
            "Cadence": [],
            "PowerCalculated": [],
            "PowerOriginal": [],
            "AirPower": [],
            "Temperature": [],
            "PerformanceCondition": [],
            "BodyBattery": [],
            "Stamina": [],
            "StaminaPotential": [],
            "GroundContactTime": [],
            "GroundContactBalance": [],
            "VerticalOscillation": [],
            "MuscleOxygenation": [],
            "MuscleOxygenation_2": [],
            "TotalHaemoglobin": [],
            "TotalHaemoglobin_2": [],
            "ImpactGsLeft": [],
            "ImpactGsRight": [],
            "BrakingGsLeft": [],
            "BrakingGsRight": [],
            "FootstrikeTypeLeft": [],
            "FootstrikeTypeRight": [],
            "PronationExcursionLeft": [],
            "PronationExcursionRight": [],
            "LegSpringStiffness": [],
            "FormPower": [],
            "RespiratoryRate": [],
            "LeftRightBalance": [],
            "Grit": [],
            "Flow": [],
            "Strokes": [],
            "StrokeType": [],
            "LeftTorqueEffectiveness": [],
            "RightTorqueEffectiveness": [],
            "LeftPedalSmoothness": [],
            "RightPedalSmoothness": [],
            "PlatformCenterOffsetLeft": [],
            "PlatformCenterOffsetRight": [],
            "LeftPowerPhaseStartAngle": [],
            "LeftPowerPhaseEndAngle": [],
            "LeftPowerPhasePeakStartAngle": [],
            "LeftPowerPhasePeakEndAngle": [],
            "RightPowerPhaseStartAngle": [],
            "RightPowerPhaseEndAngle": [],
            "RightPowerPhasePeakStartAngle": [],
            "RightPowerPhasePeakEndAngle": [],
            "ImpactLoadFactor": [],
            "StepSpeedLoss": [],
            "HrvIntervals": [],
            "Pauses": [],
            "FitDeviceInfo": [],
            "Events": {
                "RiderPosition": [],
                "FrontGearChange": [],
                "RearGearChange": [],
                "WorkoutSet": []
            },
            "DeveloperFields": [],
            "DeveloperFieldDescriptions": []
        }
    ]
}